getnovel/__init__.py
getnovel/__main__.py
getnovel/app/__init__.py
getnovel/app/itemloaders.py
getnovel/app/items.py
getnovel/app/middlewares.py
getnovel/app/pipelines.py
getnovel/app/settings.py
getnovel/app/spiders/__init__.py
getnovel/app/spiders/bachngocsach.py
getnovel/app/spiders/dtruyen.py
getnovel/app/spiders/metruyencv.py
getnovel/app/spiders/ptwxz.py
getnovel/app/spiders/sixnineshu.py
getnovel/app/spiders/sstruyen.py
getnovel/app/spiders/tangthuvien.py
getnovel/app/spiders/truyenchu.py
getnovel/app/spiders/truyenfull.py
getnovel/app/spiders/truyenyy.py
getnovel/app/spiders/uukanshu.py
getnovel/data/__init__.py
getnovel/data/example.png
getnovel/data/scrapy_settings.py
getnovel/data/template/mimetype
getnovel/data/template/META-INF/container.xml
getnovel/data/template/OEBPS/content.opf
getnovel/data/template/OEBPS/Images/cover.jpg
getnovel/data/template/OEBPS/Styles/gng-chapter.css
getnovel/data/template/OEBPS/Styles/sgc-nav.css
getnovel/data/template/OEBPS/Text/c1.xhtml
getnovel/data/template/OEBPS/Text/cover.xhtml
getnovel/data/template/OEBPS/Text/foreword.xhtml
getnovel/data/template/OEBPS/Text/nav.xhtml
getnovel/data/template/OEBPS/ncx/toc.ncx
getnovel/utils/__init__.py
getnovel/utils/arguments.py
getnovel/utils/crawler.py
getnovel/utils/epub.py
getnovel/utils/file.py
getnovel/utils/gooey_gui.py
getnovel/utils/typehint.py
getnovel_khangit-1.4.0.dist-info/LICENSE
getnovel_khangit-1.4.0.dist-info/METADATA
getnovel_khangit-1.4.0.dist-info/WHEEL
getnovel_khangit-1.4.0.dist-info/entry_points.txt
getnovel_khangit-1.4.0.dist-info/top_level.txt
getnovel_khangit-1.4.0.dist-info/RECORD
