Metadata-Version: 2.1
Name: getnovel-khangit
Version: 1.4.0
Summary: Tool based on Scrapy framework to Get novel on websites
Author-email: Vũ Thừa Khang <vuthuakhangit@gmail.com>
License: MIT
Project-URL: Homepage, https://github.com/vtkhang/getnovel
Project-URL: Bug Tracker, https://github.com/vtkhang/getnovel/issues
Keywords: crawler,scrapy
Classifier: Framework :: Scrapy
Classifier: Programming Language :: Python :: 3.7
Classifier: Programming Language :: Python :: 3.8
Classifier: Programming Language :: Python :: 3.9
Classifier: Programming Language :: Python :: 3.10
Classifier: Programming Language :: Python :: 3.11
Classifier: Development Status :: 4 - Beta
Classifier: Environment :: Console
Classifier: Framework :: Scrapy
Classifier: Operating System :: OS Independent
Requires-Python: >=3.7
License-File: LICENSE
Requires-Dist: scrapy (>=2.7.1)
Requires-Dist: pillow (>=9.4.0)
Requires-Dist: tldextract (>=3.4.0)
Requires-Dist: gooey (>=1.0.8.1)
Requires-Dist: importlib-metadata (>=4.2.0) ; python_version < "3.8"
Requires-Dist: importlib-resources (>=5.10.2) ; python_version < "3.9"
Provides-Extra: build
Requires-Dist: build (>=0.9.0) ; extra == 'build'
Provides-Extra: dev
Requires-Dist: black (>=22.12.0) ; extra == 'dev'
Requires-Dist: ipython (>=7.34.0) ; extra == 'dev'
Requires-Dist: flake8 (>=5.0.4) ; extra == 'dev'
